[
  {
    "doc_id": "142001",
    "para_id": "142001_1",
    "type": "header",
    "level": 1,
    "text": "1. 일반사항"
  },
  {
    "doc_id": "142001",
    "para_id": "142001_2",
    "type": "header",
    "level": 2,
    "text": "1.1 목적"
  },
  {
    "doc_id": "142001",
    "para_id": "142001_3",
    "type": "paragraph",
    "text": "(1) KDS 14 20 00은 무근콘크리트, 철근콘크리트 및 프리스트레스트콘크리트 구조물을 설계, 시공 및 유지관리 단계에서 필요한 기술적 사항을 기술함으로써 콘크리트 구조물의 안전성, 사용성 및 내구성을 확보하는 것을 그 목적으로 한다."
  },
  {
    "doc_id": "142001",
    "para_id": "142001_4",
    "type": "header",
    "level": 2,
    "text": "1.2 적용 범위"
  },
  {
    "doc_id": "142001",
    "para_id": "142001_5",
    "type": "paragraph",
    "text": "(1)KDS 14 20 00은 콘크리트 구조물의 설계, 시공 및 유지관리 단계에서 필요한 일반적이고 기본적인 요구 사항을 규정한 것이다. (2)콘크리트 구조물의 설계는 이 기준에서 제시한 강도설계법을 적용하는 것을 원칙으로 한다. (3)강도설계법으로 콘크리트 구조물을 설계할 때 철근콘크리트 및 프리스트레스트콘크리트 구조물의 모든 부재는 KDS 14 20 10에서 규정하는 하중계수와 강도감소계수를 사용하여야 한다. 또한 KDS 14 20 30, KDS 14 20 40에서 요구하는 사용성과 내구성에 관한 규정도 만족시켜야 한다. (4)특별한 조사연구에 의하여 설계할 때에는 이 기준을 적용하지 않을 수 있다. 다만, 성능실험을 통한 조사연구에 의하여 설계할 때에는 재료강도의 변동성과 구조물 저항성능의 변동성을 고려한 설계근거를 명시하여야 한다."
  },
  {
    "doc_id": "142001",
    "para_id": "142001_6",
    "type": "header",
    "level": 2,
    "text": "1.3 참고 기준"
  },

  {
    "doc_id": "142001",
    "para_id": "142001_7",
    "type": "paragraph",
    "text": "내용 없음."
  },
  {
    "doc_id": "142001",
    "para_id": "142001_8",
    "type": "header",
    "level": 2,
    "text": "1.4 기호의 정의"
  },
  {
    "doc_id": "142001",
    "para_id": "142001_9",
    "type": "paragraph",
    "text": "내용 없음."
  },
  

  {
    "doc_id": "142001",
    "para_id": "142001_10",
    "type": "header",
    "level": 2,
    "text": "1.5 기호의 정의"
  },
  {
    "doc_id": "142001",
    "para_id": "142001_11",
    "type": "paragraph",
    "text": "∙$A_{c}$ : 부재의 단면적, mm2 ∙$E_{c}$ : 콘크리트의 탄성계수, MPa ∙$E_{ci}$ : 재령 28일에서 콘크리트의 초기접선탄성계수, MPa ∙$E_{ci}(t')$ : 재령 $t$일에서 콘크리트의 초기접선탄성계수, MPa ∙$E_{s}$ : 철근의 탄성계수, MPa ∙$f_{c}(t')$ : 재령 $t$일에서 콘크리트의 압축응력, MPa ∙$f_{ck}$ : 콘크리트의 설계기준압축강도, MPa ∙$f_{cr}$ : 콘크리트의 배합강도, MPa ∙$f_{cm}$ : 콘크리트의 평균 압축강도, MPa ∙$f_{cm}(t)$ : 재령 $t$일에서 콘크리트의 평균 압축강도, MPa ∙$h$ : 개념부재 치수, mm $=$$2A_{c}/u$ ∙$RH$ : 외기의 상대습도, % ∙$s$ : 표준편차, MPa ∙$t~$ : 콘크리트의 재령, 일(day) ∙$t'~$ : 하중이 가해질 때의 재령, 일(day) ∙$t_{s~}$ : 콘크리트가 외기 중에 노출되었을 때의 재령, 일(day) ∙$t'_{T}$ : 온도가 20 ℃가 아닌 $T$ ℃에서 양생할 경우 등가재령, 일(day) ∙$T$  : 외기 또는 양생온도, ℃ ∙$u$ : 단면적 $A_c$의 둘레 중에서 수분이 외기로 확산되는 둘레길이, mm ∙$\\beta (f_{cm})$ : 콘크리트 강도가 크리프에 미치는 영향함수, 식 (3.1-5) 참조 ∙$\\beta (t')$ : 지속하중이 가해지는 시간 $t$가 크리프에 미치는 영향함수, 식 (3.1-6) 참조 ∙$\\beta _c(t－t')$ : 재하기간에 따라 크리프에 미치는 영향함수, 식 (3.1-7) 참조 ∙$\\beta _cc(t)$ : 콘크리트 강도 발현에 대한 재령에 따른 보정계수 ∙$\\beta _H$ : 외기의 상대습도와 부재의 두께에 따른 계수, 식 (3.1-7)과 식 (3.1-8) 참조 ∙$\\beta _H,T$ : 온도변화에 따라 보정된 $\\beta _H$, 식 (3.1-14) 참조 ∙$\\beta _{RH}$ : 외기습도에 따른 크리프와 수축에 미치는 영향계수, 식 (3.1-21) 참조 ∙$\\beta _s(t－t_s)$ : 건조기간에 따른 수축 변형률 함수, 식 (3.1-22) 참조 ∙$\\beta _{sc}$ : 시멘트 종류에 따른 수축에 미치는 영향계수 ∙$\\varepsilon _{c\\sigma }(t,t')$ : 재령 $t$일에서 $f_c(t')$의 응력이 가해졌을 때 시간 $t$일에서 탄성변형률과 크리프를 포함한 전체 변형률 ∙$\\varepsilon _{sh}(t,t_s)$ : 재령 $t_s$에서 외기에 노출된 콘크리트의 재령 $t$에서 전체 수축변형률 ∙$\\varepsilon _{sho}$ : 개념 수축계수, 식 (3.1-19) 참조 ∙$\\phi (t,t')$ : 콘크리트의 크리프계수 ∙$\\phi _o$ : 콘크리트의 개념 크리프계수, 식 (3.1-3) 참조 ∙$\\phi _{o,k}$ : 작용 응력의 크기에 따라 보정된 $\\phi _o$, 식 (3.1-11) 참조 ∙$\\phi _{RH}$ : 외기의 상대습도와 부재 두께가 크리프에 미치는 영향계수, 식 (3.1-4) 참조 ∙$\\phi _{RH,T}$ : 온도변화에 따라 보정된 $\\phi _{RH}$, 식 (3.1-13) 참조"
  },
  {
    "doc_id": "142001",
    "para_id": "142001_12",
    "type": "header",
    "level": 2,
    "text": "1.6 설계고려사항"
  },
  {
    "doc_id": "142001",
    "para_id": "142001_13",
    "type": "paragraph",
    "text": "(1)콘크리트 구조물은 구조 형식, 계수하중과 사용하중을 받을 때의 구조적 거동, 재료성질 및 합성작용, 시공성 및 비용, 환경, 미관을 고려하여, 기본적으로 구조물의 안전성, 사용성 및 내구성이 확보되도록 책임구조기술자가 설계하여야 하며, 특별한 요구가 있는 경우에는 구조물의 특성에 따른 추가조건을 고려하여 설계하여야 한다. (2)충돌과 폭발 등 극단상황에 대한 발주자 또는 건축주의 특별한 요구가 있는 경우에는 이를 고려하여 설계하여야 한다. (3)화재에 대한 발주자 또는 건축주의 특별한 요구가 있는 경우에는 해당 법령에 따라 내화 요구 조건을 만족하도록 설계하여야 한다. (4)시공하중의 극한상태 유발 가능성에 대한 발주자 또는 건축주의 특별한 요구가 있는 경우에는 시공단계 및 시공하중을 고려하여 설계하여야 한다. (5)구조물 손상 후의 복구성을 고려한 발주자 또는 건축주의 특별한 요구가 있는 경우에는 이를 고려하여 설계하여야 한다. (6)물리적, 화학적, 생물학적으로 유해한 상황을 고려한 발주자 또는 건축주의 특별한 요구가 있는 경우에는 이를 고려하여 설계하여야 한다."
  },
  {
    "doc_id": "142001",
    "para_id": "142001_14",
    "type": "header",
    "level": 2,
    "text": "1.7 구조설계도서"
  },
  {
    "doc_id": "142001",
    "para_id": "142001_15",
    "type": "paragraph",
    "text": "(1)구조설계도는 구조평면도와 구조계산에 의하여 산정된 부재의 단면 및 접합부 상세를 표현하고, 아울러 구조계산에는 포함되지 않았으나 구조실험이나 경험 등으로 구조 안전이 확인된 관련 상세까지도 표현하여 구조설계 취지에 부합되도록 작성하여야 한다. (2)구조설계도는 설계의 진척도에 따라 계획설계, 기본설계, 실시설계의 3단계로 나누어 작성할 수 있다. (3)구조설계 도서에는 공사에 꼭 필요한 적절한 주기사항을 포함하여야 하며, 신속 정확하게 찾아볼 수 있게 정해진 양식 속에 모든 관련 정보를 포함하여야 한다. 이러한 도서들은 책임구조기술자의 구조설계 의도를 명확히 전달하고, 배근시공도 작성을 위한 배근형태의 지침이 되어야 한다. (4)구조설계 도서에 포함되어야 하는 내용은 다음과 같다. ① 구조설계 관련 기준 ② 활하중 등 주요 설계하중 ③ 구조재료 강도 ④ 구조 부재의 크기 및 위치, 단면, 상대적인 위치 ⑤ 철근과 앵커의 규격, 설치 위치 ⑥ 철근의 정착길이, 이음의 위치 및 길이, 이음의 종류 ⑦ 바닥 높이, 기둥중심과 오프셋 및 요철부의 치수 ⑧ 접합의 유형 ⑨ 솟음이 필요할 경우 위치, 방향 및 크기 ⑩ 부구조체의 시공 상세도 작성에 필요한 경우 상세기준 ⑪ 기타 구조 시공 상세도 작성에 필요한 상세와 자료 ⑫ 책임구조기술자, 자격명 및 소속회사명, 연락처 ⑬ 구조설계 연월일"
  },
  {
    "doc_id": "142001",
    "para_id": "142001_16",
    "type": "header",
    "level": 1,
    "text": "2. 조사 및 계획"
  },
  {
    "doc_id": "142001",
    "para_id": "142001_17",
    "type": "paragraph",
    "text": "내용 없음."
  },
  {
    "doc_id": "142001",
    "para_id": "142001_18",
    "type": "header",
    "level": 1,
    "text": "3. 재료"
  },
  {
    "doc_id": "142001",
    "para_id": "142001_19",
    "type": "paragraph",
    "text": "(1) KDS 14 20 00에 따라 콘크리트 구조 부재를 설계할 때 사용하는 재료의 품질과 시험은 이 기준의 규정 및 KCS 14 20 10에 따라야 한다."
  },
  {
    "doc_id": "142001",
    "para_id": "142001_20",
    "type": "header",
    "level": 2,
    "text": "3.1 콘크리트"
  },
  {
    "doc_id": "142001",
    "para_id": "142001_21",
    "type": "header",
    "level": 3,
    "text": "3.1.1 구성재료"
  },
  {
    "doc_id": "142001",
    "para_id": "142001_22",
    "type": "paragraph",
    "text": "(1)시멘트는 한국산업표준 KS L 5201, KS L 5205, KS L 5210, KS L 5211, KS L 5217, KS L 5401에 규정한 것과 같거나 또는 이와 동등 이상의 것을 사용하여야 한다. (2)골재의 품질과 크기는 다음의 규정에 따라야 한다. ① 골재는 한국산업표준에 규정한 것과 같거나 또는 이와 동등 이상의 것을 사용하여야 한다. ② 골재는 적당한 경도나 입도를 가지며 깨끗하고 내구성이 있는 것으로, 점토 덩어리, 유기물, 세장석편 등과 같은 해로운 물질을 포함하지 말아야 하며, KS F 2527, KS F 2573에 규정된 품질로 하여야 한다. ③ 위 규격품이 아닌 경우 KS F 2502, KS F 2503, KS F 2504, KS F 2529, KS F 2533, KS F 2468의 골재와 관련된 한국산업표준에 규정한 것과 같거나 또는 이와 동등 이상의 것을 사용하여야 한다. 그리고 이외에는 시험에서 적당한 입도로서 소요품질의 콘크리트를 만들 수 있다고 입증되는 경우에만 책임구조기술자의 승인을 얻은 후에 사용할 수 있다. ④ 굵은 골재의 최대 공칭치수는 다음 값을 초과하지 말아야 한다. 그러나 이러한 제한은 콘크리트를 공극 없이 칠 수 있는 다짐 방법을 사용할 경우에는 책임구조기술자의 판단에 따라 적용하지 않을 수 있다. 가. 거푸집 양 측면 사이의 최소 거리의 1/5 나. 슬래브 두께의 1/3 다. 개별 철근, 다발철근, 긴장재 또는 덕트 사이 최소 순간격의 3/4 (3)화학혼화제의 품질과 사용은 다음 규정에 따라야 한다. ① 화학혼화제는 KS F 2560에 규정한 것과 같거나 또는 이와 동등 이상의 것을 사용하여야 한다. ② 화학혼화제를 사용할 경우에는 충분한 품질조사와 시험을 거친 후 책임구조기술자의 승인을 얻어야 한다. ③ 화학혼화제는 콘크리트 배합을 결정할 때에 사용했던 제품과 동일한 성분 및 성능을 공사 중 일관되게 유지하여야 한다. ④ 염화칼슘 또는 염화물을 포함하는 화학혼화제는 프리스트레스트콘크리트, 알루미늄 제품을 매입한 콘크리트 또는 아연 도금한 고정형 금속 형틀을 사용한 콘크리트의 경우에 사용할 수 없다. (4)콘크리트를 제조할 때 사용되는 물은 다음 규정에 따라야 한다. ① 콘크리트 배합에 사용되는 물은 청정한 것으로서 일반적으로 산, 기름, 알칼리, 염분, 유기물 그리고 콘크리트 및 철근에 유해한 물질을 포함하지 말아야 한다. ② 콘크리트의 배합에 사용되는 물은 KS F 4009 부속서 B에 적합한 것이어야 한다. ③ 프리스트레스트콘크리트 또는 알루미늄 제품을 매입한 콘크리트의 배합에 사용하는 물과 골재의 표면수는 유해량의 염화물을 함유하지 말아야 한다. 염소이온의 유해량에 대한 것은 KCS 14 20 10 (1.9.1)의 규정을 참조할 수 있다. ④ 식수로서 부적당한 물은 다음에 열거한 사항을 만족하지 못하면 콘크리트에 사용될 수 없다. 가. 동일 수원의 물을 사용하여 이에 적절한 배합설계를 하여야 한다. 나. 식수로 적합하지 않은 물로 만들어진 모르타르 시험체의 7일과 28일 강도는 식수로 만들어진 같은 형태의 공시체 강도의 90% 이상의 강도를 각각 가져야 한다. 사용한 물의 차이에 따른 강도비교 시험은 물 이외에는 같은 조건의 모르타르를 사용하여 실시하고, 그 시험을 KS L 5105에 따라 준비, 시험하여야 한다. (5)콘크리트를 제조할 때 사용되는 혼화재료는 다음 규정에 따라야 한다. ① 혼화재로 사용할 플라이애쉬는 KS L 5405에 적합한 것이어야 한다. ② 혼화재로 사용할 콘크리트용 팽창재는 KS F 2562에 적합한 것이어야 한다. ③ 혼화재로 사용할 고로슬래그 미분말은 KS F 2563에 적합한 것이어야 한다. ④ 혼화재로 사용할 실리카퓸은 KS F 2567에 적합한 것이어야 한다. ⑤ ①, ② 및 ③ 이외의 혼화재인 규산질 미분말 및 고강도용 혼화재 등을 사용할 때는, 이들 혼화재에 대하여 아직 품질의 규격이 없고 또 사용 방법도 다양하므로 미리 충분히 조사, 시험을 하여 품질을 확인하고 사용 방법도 검토하여 제조한 콘크리트의 내구성에 영향이 없도록 하여야 한다."
  },
  {
    "doc_id": "142001",
    "para_id": "142001_23",
    "type": "header",
    "level": 3,
    "text": "3.1.2 콘크리트 일반"
  },
  {
    "doc_id": "142001",
    "para_id": "142001_24",
    "type": "paragraph",
    "text": "(1)콘크리트 공시체의 제작 및 양생 방법은 KS F 2403에 따라 제작하고 양생하는 방법에 따라야 한다. 콘크리트의 공시체를 제작할 때 압축강도용 공시체는 $\\phi 150\\times 300$mm를 기준으로 하며, $\\phi 100\\times 200$mm의 공시체를 사용할 경우 강도보정계수 0.97을 사용하며, 이외의 경우에도 적절한 강도보정계수를 고려하여야 한다. (2)레디믹스트콘크리트를 사용하는 경우에는 KCS 14 20 01을 따르되, 시공기준에 명시되지 않은 사항은 KS F 4009에 따라야 한다. (3)경량콘크리트 제조용 경량콘크리트 골재는 KS F 2527에 규정하는 구조용 경량골재를 사용하여야 한다. (4)콘크리트를 친 후 28일 이내에 부재의 원래 설계하중이나 응력을 받지 않은 경우, 부재의 압축강도는 책임구조기술자가 승인하는 경우 재령에 따른 증가계수를 곱할 수 있다. 이때 식 (3.1-15)와 식 (3.1-16)을 사용할 수 있다. (5)콘크리트의 크리프는 다음의 규정에 따라 예측할 수 있다. ① 시간 $t$에서 작용 응력 $f_c(t')$에 의한 콘크리트의 순간 변형 및 크리프 변형을 함께 고려한 전체 변형률 $\\varepsilon _{{c}{\\sigma }}(t,~t')$는 콘크리트의 압축강도 또는 설계기준압축강도, 부재의 크기, 평균 상대습도, 재하할 때의 재령, 재하기간, 시멘트 종류, 양생온도, 온도변화, 작용 응력의 크기 등에 따라 식 (3.1-1)을 사용하여 구할 수 있다."
  },
  {
    "doc_id": "142001",
    "para_id": "142001_25",
    "type": "paragraph",
    "text": "$\\varepsilon _{c\\sigma }(t,t')＝f_{c}(t')\\left [\\frac{1}{E_{ci} (t')}＋{\\phi (t,t')}over{E_{ci}}\\right ]$\t(3.1-1)"
  },
  {
    "doc_id": "142001",
    "para_id": "142001_26",
    "type": "paragraph",
    "text": "여기서, $E_{ci}$는 KDS 14 20 10(식 (4.3-4))에 의해 구하고, $E_{ci}(t')$는 식 (3.1-17)에 의해서 구하여야 한다. ② 식 (3.1-1)에서 크리프계수 $\\phi (t,t')$는 양생온도가 20 ℃이고, 하중이 작용하는 동안의 대기온도 20 ℃인 경우를 기준으로 한 것으로서 다음과 같이 구할 수 있다."
  },
  {
    "doc_id": "142001",
    "para_id": "142001_27",
    "type": "paragraph",
    "text": "$\\phi (t,t')＝\\phi _{o}\\beta _{c}(t－t')$\t(3.1-2)"
  },
  {
    "doc_id": "142001",
    "para_id": "142001_28",
    "type": "paragraph",
    "text": "여기서, 각 변수는 다음과 같다."
  },
  {
    "doc_id": "142001",
    "para_id": "142001_29",
    "type": "paragraph",
    "text": "$\\phi _{o}＝\\phi _{RH}\\beta (f_{cm})\\beta (t')$ \t(3.1-3) $\\phi_{RH}＝1＋\\frac{1－0.01RH}{0.10root{3} of{h}}$\t(3.1-4) $\\beta (f_{cm})＝\\frac{16.8}{\\sqrt {f_{cm} }}$\t (3.1-5) $\\beta(t')＝\\frac{1}{0.1＋(t')^{0.2}}$\t(3.1-6) $\\beta_{c}(t－t')＝ \\left[ \\frac{(t－t' )}{\\beta   _{H}'＋(t－t' )} \\right]  ^{0.3}$  (3.1-7) $\\beta _{H}＝1.5\\left [1＋(0.012RH)^{18}\\right ]h＋250\\leq 1,500(일)$\t(3.1-8)"
  },
  {
    "doc_id": "142001",
    "para_id": "142001_30",
    "type": "paragraph",
    "text": "그리고 여기서 $f_{cm}$은 KDS 14 20 10(식 (4.3-3))을 따른다. ③ 작용 응력의 크기, 온도 및 시멘트의 종류에 따라 식 (3.1-2)의 크리프계수는 다음과 같이 보정하여야 한다. 가. 양생온도 및 시멘트 종류에 따른 보정계수 양생 동안 온도의 변화가 있거나 20 ℃가 아닌 대기에 노출되어 있는 경우, 재하할 때의 콘크리트 재령 $t$는 온도와 시멘트 종류를 고려하여 다음과 같이 보정하여야 한다."
  },
  {
    "doc_id": "142001",
    "para_id": "142001_31",
    "type": "paragraph",
    "text": "$t'=t'_{T}\\left [\\frac{9}{2+(t'_{T} )^{1.2}}+1\\right ]^{\\alpha }\\geq 0.5(일)$\t(3.1-9) $t'_{T}＝\\sum_{i=1}^{n}\\Delta t_{i} * exp\\left (－\\frac{4,000}{273＋T(\\Delta t_{i} )}＋13.65\\right)$ (3.1-10)"
  },
  {
    "doc_id": "142001",
    "para_id": "142001_32",
    "type": "paragraph",
    "text": "$\\alpha ＝－1~:2종~시멘트$ $\\alpha ＝－0~:1,5종~시멘트$ $\\alpha ＝1~:3종~시멘트$"
  },
  {
    "doc_id": "142001",
    "para_id": "142001_33",
    "type": "paragraph",
    "text": "여기서, $T(\\Delta t_i)$는 $\\Delta t_i$일 동안 지속된 온도(℃), $\\Delta t_i$는 일정한 온도가 지속된 기간(일)이고, $n$은 일정한 온도를 유지한 단계의 수이다."
  },
  {
    "doc_id": "142001",
    "para_id": "142001_34",
    "type": "paragraph",
    "text": "나. 작용 응력의 크기에 따른 보정계수 작용 응력 $f_{c}(t')$가 $0.4f_{cm}(t')<｜f_{c}(t')｜$$<0.6f_{cm}(t')$인 경우 식 (3.1-3)의 $\\phi _{o}$를 식 (3.1-11)과 같이 보정하여 크리프의 비선형성을 고려하여야 한다."
  },
  {
    "doc_id": "142001",
    "para_id": "142001_35",
    "type": "paragraph",
    "text": "$\\phi _{o,k}＝\\phi _{o} exp \\left[1.5\\left (\\frac{｜f_{c}(t')｜}{f_{cm}(t')}－0.4\\right ) \\right]$\t(3.1-11)"
  },
  {
    "doc_id": "142001",
    "para_id": "142001_36",
    "type": "paragraph",
    "text": "여기서, $f_{cm}(t')$는 식 (3.1-15)와 식 (3.1-16)에 의해 구할 수 있다. 다. 온도변화에 따른 보정계수 지속하중이 작용하는 동안 온도가 5 ℃에서 80 ℃까지 변화할 때 크리프계수는 식 (3.1-4)의 $\\phi _RH$를 식 (3.1-13)으로, 그리고 식 (3.1-8)의 $\\beta _H$를 식 (3.1-14)로 보정하여 식 (3.1-12)에 의해 구하여야 한다."
  },
  {
    "doc_id": "142001",
    "para_id": "142001_37",
    "type": "paragraph",
    "text": "$\\phi (t,t')＝\\beta _c(t－t')\\phi _o＋0.0004(T－20)^2$ \t(3.1-12) $\\phi _{RH,T}＝\\phi _T+(\\phi _RH-1.0)\\phi _T^1.2$\t(3.1-13) 여기서, $\\phi _{T}=exp[0.015(T－20)]$"
  },
  {
    "doc_id": "142001",
    "para_id": "142001_38",
    "type": "paragraph",
    "text": "$\\beta _{H,T}=exp\\left [\\frac{1,500}{273+T}-5.12\\right ]\\beta _H$\t (3.1-14)"
  },
  {
    "doc_id": "142001",
    "para_id": "142001_39",
    "type": "paragraph",
    "text": "④ 28일 평균 압축강도 $f_{cm}$은  KDS 14 20 10(식 (4.3-3))으로 구하며, 시간에 따른 콘크리트의 강도발현 $f_{cm}(t)$는 식 (3.1-15)와 같이 구할 수 있다."
  },
  {
    "doc_id": "142001",
    "para_id": "142001_40",
    "type": "paragraph",
    "text": "$f_{cm}(t)＝\\beta _{cc}(t)f_{cm}$\t(3.1-15) $\\beta_{cc}(t)＝exp \\left[\\beta _{sc}\\left (1－\\sqrt {\\frac{28}{t} }\\right ) \\right]$\t(3.1-16)"
  },
  {
    "doc_id": "142001",
    "para_id": "142001_41",
    "type": "paragraph",
    "text": "$$ \\beta _{sc}=0.35:1종시멘트습윤양생, =0.15:1종시멘트증기양생, =0.25:3종시멘트습윤양생, =0.12:3종시멘트증기양생, = 0.40:2종시멘트 $$"
  },
  {
    "doc_id": "142001",
    "para_id": "142001_42",
    "type": "paragraph",
    "text": "여기서, $\\beta _{cc}(t)$는 시간에 따른 강도발현속도이고, $\\beta _{sc}$는 시멘트 종류에 따른 상수이다."
  },
  {
    "doc_id": "142001",
    "para_id": "142001_43",
    "type": "paragraph",
    "text": "⑤ 크리프 변형을 계산할 때 콘크리트의 초기접선탄성계수는 KDS 14 20 10(식 (4.3-4))로 구하여야 한다. 한편, 초기접선탄성계수 $E_{ci}(t)$의 시간에 따른 변화는 다음 식 (3.1-17)과 같이 구하여야 하며 $\\beta _{cc}(t)$는 식 (3.1-16)과 같다."
  },
  {
    "doc_id": "142001",
    "para_id": "142001_44",
    "type": "paragraph",
    "text": "$E_{ci}(t)＝\\sqrt {\\beta _{cc}(t)}E_{ci}$\t(3.1-17)"
  },
  {
    "doc_id": "142001",
    "para_id": "142001_45",
    "type": "paragraph",
    "text": "⑥ 크리프에 대한 실험은 KS F 2453에 따라야 한다. (6)콘크리트의 수축 변형률은 대기의 평균 상대습도, 부재의 크기 등을 고려하여 다음 식 (3.1-18)에 따라 구할 수 있다."
  },
  {
    "doc_id": "142001",
    "para_id": "142001_46",
    "type": "paragraph",
    "text": "$\\varepsilon _{sh}(t,t_{s})＝\\varepsilon _{sho}\\beta _{s}(t－t_{s})$\t(3.1-18)"
  },
  {
    "doc_id": "142001",
    "para_id": "142001_47",
    "type": "paragraph",
    "text": "여기서, $\\varepsilon _{sho}$와 $\\beta _{s}(t－t_{s})$는 다음 식 (3.1-19)에서 식 (3.1-22)까지에 의해 계산하여야 한다."
  },
  {
    "doc_id": "142001",
    "para_id": "142001_48",
    "type": "paragraph",
    "text": "$\\varepsilon _{sho}＝\\varepsilon _{s}(f_{cm})\\beta _{RH}$\t(3.1-19) $\\varepsilon _{s}(f_{cm})＝\\left [160＋10\\beta _{sc}(9－f_{cm}/10)\\right ]\\times 10^{－6}$\t(3.1-20)"
  },
  {
    "doc_id": "142001",
    "para_id": "142001_49",
    "type": "paragraph",
    "text": "$\\beta _{RH}=-1.55[1-(RH/100)^{3} when (40\\%\\leq RH<99\\%)$ $\\beta _{RH}=0.25  when (RH\\geq 99\\%)$ (3.1-21)"
  },
  {
    "doc_id": "142001",
    "para_id": "142001_50",
    "type": "paragraph",
    "text": "$\\beta _{s}(t－t_{s})＝~\\sqrt {\\frac{(t－t_{s})}{0.035h^{2} ＋(t－t_{s})}}$\t(3.1-22)"
  },
  {
    "doc_id": "142001",
    "para_id": "142001_51",
    "type": "paragraph",
    "text": "$$ \\beta _{sc}＝4~:2종~시멘트 \\beta _{sc}＝5~:1종,5종~시멘트 \\beta _{sc}＝8~:3종~시멘트 $$"
  },
  {
    "doc_id": "142001",
    "para_id": "142001_52",
    "type": "paragraph",
    "text": "외기의 온도가 20 ℃가 아닌 경우 $\\beta _{RH}$ 및 $\\beta _{s}(t－t_{s})$는 다음 식 (3.1-23)과 식 (3.1-24)에 의해 보정하여야 한다."
  },
  {
    "doc_id": "142001",
    "para_id": "142001_53",
    "type": "paragraph",
    "text": "$\\beta _{RH,T}=\\left [1+\\left (\\frac{8}{103}-RH\\right )\\left (\\frac{T-20}{40}\\right )\\right ]\\beta _{RH}$\t(3.1-23)"
  },
  {
    "doc_id": "142001",
    "para_id": "142001_54",
    "type": "paragraph",
    "text": "$$ \\beta _{s}(t－t_{s})＝\\sqrt {\\frac{(t－t_{s})}{0.035h^{2} exp[－0.06(T－20)]＋(t－t_{s})}} $$ (3.1-24)"
  },
  {
    "doc_id": "142001",
    "para_id": "142001_55",
    "type": "header",
    "level": 3,
    "text": "3.1.3 시험 일반"
  },
  {
    "doc_id": "142001",
    "para_id": "142001_56",
    "type": "paragraph",
    "text": "(1)콘크리트는 KDS 14 20 40 규정을 만족시키도록 배합하여야 할 뿐만 아니라, 3.1.4(2)에서 규정한 배합강도가 확보되도록 배합하여야 하고, 콘크리트를 생산할 때 3.1.5(2)③에서 규정한 바와 같이 $f_{ck}$ 미만의 강도가 나오는 빈도를 최소화하여야 한다. (2)$f_{ck}$에 대한 요구 조건은 3.1.5(2)에서 기술한 것과 같이 공시체 제작 및 시험 규정에 의해 시행한 원주공시체의 시험에 근거를 두어야 한다. (3)특별히 다른 규정이 없을 경우 $f_{ck}$는 재령 28일 강도를 기준으로 하여야 한다. 다른 재령에서 시험을 한 경우에는 $f_{ck}$의 시험 일자를 설계도나 공사시방서에 명기하여야 한다. (4)콘크리트의 쪼갬인장강도 $f_{sp}$에 관한 KDS 14 20 10(4.3.4(1)②)의 설계규정을 적용하여야 할 경우, 규정된 $f_{ck}$값에 해당하는 $f_{sp}$의 값을 설정하기 위한 시험실 시험을 실시하여야 한다. (5)쪼갬인장강도 시험 결과를 현장 콘크리트의 적합성 판단 기준으로 사용할 수 없다."
  },
  {
    "doc_id": "142001",
    "para_id": "142001_57",
    "type": "header",
    "level": 3,
    "text": "3.1.4 배합의 선정"
  },
  {
    "doc_id": "142001",
    "para_id": "142001_58",
    "type": "paragraph",
    "text": "(1)표준편차의 설정은 다음에 따라야 한다. ① 콘크리트 생산설비의 시험기록이 있을 경우, 이에 대한 표준편차를 산정하여야 한다. 표준편차의 산정에 사용할 수 있는 시험기록은 다음과 같다. 가. 예상되는 실제 상황과 비슷한 재료, 품질관리 절차 및 조건들을 갖추어야 하며, 시험기록에 사용된 재료와 배합비의 변화폭이 실제 현장에 적용되는 것과 유사한 조건에서 작성된 것이어야 한다. 나. 계획된 공사에서 요구하는 설계기준압축강도와 같거나 혹은 설계기준압축강도에서 그 차이가 7MPa 이내의 강도를 갖는 콘크리트에 의해 구해진 값이어야 한다. 다. 다음 ②에서 요구하는 것을 제외하고 적어도 30회의 연속시험을 실시하여야 한다. ② 콘크리트 생산설비가 상기 ①의 요건에 맞는 시험기록을 갖고 있지 않지만 15회 이상, 29회 이하의 연속시험의 기록을 갖고 있는 경우, 표준편차는 계산된 표준편차와 표 3.1-1의 보정계수의 곱으로 계산할 수 있다. 시험기록을 인정받기 위해서 상기 ①의 가와 나의 요건과 일치하고, 또한 45일 이상의 기간 동안 실시된 연속시험한 기록이어야 한다."
  },
  {
    "doc_id": "142001",
    "para_id": "142001_59",
    "type": "paragraph",
    "text": "표 3.1-1 시험이 29회 이하일 때 표준편차에 대한 보정계수"
  },
  {
    "doc_id": "142001",
    "para_id": "142001_60",
    "type": "paragraph",
    "text": "(2)배합강도는 다음에 따라 결정하여야 한다. ① 콘크리트 배합을 선정할 때 기초하는 배합강도 $f_cr$은 3.1.4(1)의 규정에 따라 계산된 표준편차를 이용하여 계산한다. 이때 배합강도는 설계기준압축강도가 35MPa 이하인 경우 식 (3.1-25)와 식 (3.1-26)으로 계산된 두 값 중 큰 값으로 정하며, 또한 설계기준압축강도가 35MPa을 초과하는 경우는 식 (3.1-25)와 식 (3.1-27)로 계산된 두 값 중 큰 값으로 정한다."
  },
  {
    "doc_id": "142001",
    "para_id": "142001_61",
    "type": "paragraph",
    "text": "$f_{ck}\\leq 35$MPa인 경우, $f_{cr}=f_{ck}+1.34s$\t(3.1-25) $f_{cr}=(f_{ck}-3.5)+2.33s$\t(3.1-26)"
  },
  {
    "doc_id": "142001",
    "para_id": "142001_62",
    "type": "paragraph",
    "text": "$f_{ck}>35$MPa인 경우, $f_{cr}=f_{ck}+1.34s$\t(3.1-25) $f_{cr}=0.9f_{ck}+2.33s$\t(3.1-27)"
  },
  {
    "doc_id": "142001",
    "para_id": "142001_63",
    "type": "paragraph",
    "text": "② 배합강도 $f_{cr}$은 상기 (1)의 요건에 맞는 표준편차의 계산을 위한 현장강도 기록자료가 없을 경우 또는 압축강도의 시험횟수가 14회 이하인 경우 다음 표 3.1-2에 따라 결정하여야 한다. 표 3.1-2 시험횟수가 14회 이하이거나 기록이 없는 경우의 배합강도"
  },
  {
    "doc_id": "142001",
    "para_id": "142001_64",
    "type": "paragraph",
    "text": "(3)배합강도는 시공 중 자료 취득이 가능하면, $f_{ck}$보다 커야 하는 $f_{cr}$의 초과 값은 다음의 ①과 ③을 동시에 만족하거나 또는 ②와 ③을 동시에 만족하는 경우 감소시킬 수 있다. ① 30회 또는 그 이상의 시험결과를 이용하여 구한 시험결과의 평균이 3.1.4.(1)①에 따라 계산한 표준편차를 사용하여 계산한 상기 (2)①의 조건값을 초과한 경우 ② 29회 이하의 시험결과값이 얻어지고 그 시험결과의 평균값이 상기 (1)②의 표준편차를 사용하여 계산한 상기 (2)①의 조건값을 초과한 경우 ③ KDS 14 20 40(4.1.3)의 특수노출 필요 사항을 만족한 경우"
  },
  {
    "doc_id": "142001",
    "para_id": "142001_65",
    "type": "header",
    "level": 3,
    "text": "3.1.5 평가와 사용승인"
  },
  {
    "doc_id": "142001",
    "para_id": "142001_66",
    "type": "paragraph",
    "text": "(1)시험의 빈도는 다음 ①에서 ④까지 규정에 따라야 한다. ① 각 날짜에 친 각 등급의 콘크리트 강도시험용 시료는 다음과 같이 채취하여야 한다. 가. 하루에 1회 이상 나. 120m3 당 1회 이상 다. 슬래브나 벽체의 표면적 500m2 마다 1회 이상 라. 배합이 변경될 때마다 1회 이상 ② 콘크리트를 치는 전체량이 적어 상기 ①에 따라 행한 시험 빈도수가 어느 등급의 콘크리트 강도 시험에서도 5회보다 적을 경우 시험은 무작위로 선택한 5배치에 대하여 하거나 또는 5배치보다 적은 경우 각 배치에 대하여 실시하여야 한다. ③ 사용 콘크리트의 전체량이 40m3 보다 적을 경우 책임구조기술자의 판단으로 만족할 만한 강도라고 인정될 때는 강도 시험을 생략할 수 있다. ④ 강도시험은 똑같은 콘크리트 시료로 제작한 3개의 공시체 강도의 평균으로 하여야 하고 시험은 28일째 또는 $f_{ck}$의 결정을 위해 지정된 날에 시험하여야 한다. (2)시험실에서 양생한 공시체의 제작, 시험 및 강도는 다음 ①에서 ④까지 규정을 만족하여야 한다. ① 강도 시험용 시료는 KS F 2401에 따라 채취하여야 한다. ② 강도 시험용 공시체는 KS F 2405에 따라 시험하여야 한다. ③ 콘크리트 각 등급의 강도는 다음의 두 요건이 충족되면 만족할 만한 것으로 간주할 수 있다. 가. 3번의 연속강도 시험의 결과 그 평균값이 $f_{ck}$ 이상일 때 나. 개별적인 강도 시험값이 $f_{ck}$가 35MPa 이하인 경우에는 $f_{ck}-3.5$MPa 이상, 또한 $f_{ck}$가 35MPa 초과인 경우에는 $0.9f_{ck}$ 이상인 경우 ④ 상기 ③의 조건 중의 어느 하나라도 충족되지 않으면 다음 (4)의 규정에 따라, 시험을 통하여, 강도 시험 결과의 평균값을 증가시키는 조치를 취하여야 한다. (3)현장에서 양생한 공시체의 제작, 시험 및 강도 결과는 다음 ①에서 ④의 규정을 만족하여야 한다. ① 책임구조기술자는 실제 구조물에서 콘크리트의 보호와 양생의 적절함을 검토하기 위하여 현장 상태에서 양생된 공시체 강도의 시험을 요구할 수 있다. ② 현장 양생되는 공시체는 KS F 2403에 따라 현장 조건에서 양생하여야 한다. ③ 현장 양생되는 시험공시체는 시험실에서 양생되는 시험공시체와 똑같은 시간에 같은 시료로 만들어야 한다. ④ $f_{ck}$의 결정을 위해 지정된 시험 재령에 행한 현장 양생된 공시체 강도가 동일 조건의 시험실에서 양생된 공시체 강도의 85%보다 작을 때는 콘크리트의 양생과 보호절차를 개선하여야 한다. 만일 현장 양생된 것의 강도가 $f_{ck}가$ 35MPa 이하인 경우 $f_{ck}$보다 3.5MPa을 더 초과하거나, $f_{ck}$가 35MPa 초과인 경우 $f_{ck}$보다 0.1$f_{ck}$를 더 초과하면 85%의 한계조항은 무시할 수 있다. (4)시험결과 콘크리트의 강도가 작게 나온 경우 다음 절차에 따라야 한다. ① 시험실에서 양생된 공시체 개개의 압축 시험 결과가 상기 (1)④의 $f_{ck}$보다 $f_{ck}$가 35MPa 이하인 경우 3.5MPa 이상 낮거나, $f_{ck}$가 35MPa 초과인 경우 0.1$f_{ck}$ 이상 낮거나 또는 현장에서 양생된 공시체의 시험결과에서 상기 (3)④에서 기술된 결점이 나타나면, 구조물의 하중지지 내력이 부족하지 않도록 적절한 조치를 취하여야 한다. ②콘크리트 강도가 현저히 부족하다고 판단될 때, 그리고 계산에 의해 하중저항 능력이 크게 감소되었다고 판단될 때, 문제된 부분에서 코어를 채취하고 채취된 코어의 시험은 KS F 2422에 따라 수행하여야 한다. 이때 강도 시험값이 $f_{ck}$가 35MPa 이하인 경우 $f_{ck}$보다 3.5MPa 이상 부족하거나 또는 $f_{ck}$가 35MPa 초과인 경우 0.1$f_{ck}$ 이상 부족한지 여부를 알아보기 위하여 3개의 코어를 채취하여야 한다. ③구조물에서 콘크리트 상태가 건조된 경우 코어는 시험 전 7일 동안 공기(온도 15~30 ℃, 상대습도 60% 이하)로 건조시킨 후 기건상태에서 시험하여야 한다. 구조물의 콘크리트가 습윤된 상태에 있다면 코어는 적어도 40시간 동안 물속에 담가두어야 하며 습윤상태로 시험하여야 한다. ④ 코어 시험에서 만일 코어 공시체 3개의 평균값이 $f_{ck}$의 85%에 달하고, 각각의 코어 강도가 $f_{ck}$의 75%보다 작지 않으면 구조적으로 적합하다고 판정할 수 있다. 시험의 정확성을 위하여 불규칙한 코어 강도를 나타내는 위치에 대해서 재시험을 실시하여야 한다. ⑤ 상기 (4)④의 규정과 일치되지 않고 구조적 적합성이 의심스러울 때 책임구조기술자는 구조물의 의심스러운 부분에 대해서 KDS 14 20 90의 규정에 따라 구조물의 재하시험을 지시하거나 기타 적당한 조치를 취하여야 한다."
  },
  {
    "doc_id": "142001",
    "para_id": "142001_67",
    "type": "header",
    "level": 3,
    "text": "3.1.6 시험"
  },
  {
    "doc_id": "142001",
    "para_id": "142001_68",
    "type": "paragraph",
    "text": "(1)책임구조기술자가 공사진행 중 필요하다고 인정할 경우 보통중량콘크리트의 시험은 다음에 따라야 한다. ① 강도의 평가는 KS F 2405, KS F 2408, KS F 2423을 따라야 한다. ② 단위용적질량 시험은 KS F 2409를 따라야 한다. ③ 블리딩 시험은 KS F 2414를 따라야 한다. ④ 공기량 시험은 KS F 2409 및 KS F 2421을 따라야 한다. ⑤ 슬럼프 시험은 KS F 2402를 따라야 한다. (2)경량콘크리트의 시험은 다음 규정을 따라야 한다. ① 단위용적질량 시험은 KS F 2462를 따라야 하며, KS F 2527의 규정에도 적합하여야 한다. ② 불순물 시험 방법은 KS F 2468을 따라야 한다. ③ 기타 시험은 보통중량콘크리트 시험 방법을 따라야 한다."
  },
  {
    "doc_id": "142001",
    "para_id": "142001_69",
    "type": "header",
    "level": 2,
    "text": "3.2 강재"
  },
  {
    "doc_id": "142001",
    "para_id": "142001_70",
    "type": "header",
    "level": 3,
    "text": "3.2.1 강재일반"
  },
  {
    "doc_id": "142001",
    "para_id": "142001_71",
    "type": "paragraph",
    "text": "(1)보강용 철근은 이형철근을 사용하여야 한다. 다만, 나선철근이나 강선으로 원형철근을 사용할 수 있다. 그리고 구조용 강재, 강관에 의한 보강재는 이 설계기준에 따라 사용될 수 있다. (2)철근을 용접하는 경우 그 위치와 용접 방법을 명기하여야 한다. 필요한 용접기호는 KS B 0052에 따르며, 용접 검사는 KS B 0816,  KS B 0845,  KS B 0896, KS D 0213, KS B ISO17660-1, KS B ISO17660-2 중 해당되는 검사를 실시한다. (3)철근, 철선 및 용접철망의 품질, 형상, 치수는 KS D 3504, KS D 3552와 KS D 7017의 각 규격에 적합하여야 한다. (4)철근, 철선 및 용접철망의 응력-변형률 곡선에서 항복점이 뚜렷하게 나타나는 경우에는 항복점에서의 응력을 항복강도 $f_{y}$로 결정한다. 항복점이 뚜렷하게 나타나지 않는 경우에는 0.2% 오프셋법을 적용하여, 0.002의 변형률에서 강재의 탄성계수와 같은 기울기로 직선을 그은 후 응력-변형률 곡선과 만나는 점의 응력을 항복강도 $f_{y}$로 결정하여야 한다. (5)철근은 아연도금 또는 에폭시수지 도막이 가능하며, 이들 철근은 KS D 3629의 규정을 따라야 한다. (6)긴장재는 다음 규정을 따라야 한다. ① 프리스트레스트콘크리트에 사용되는 강선은 KS D 7002의 규정에 따라야 한다. ② 강봉에 관한 것은 KS D 3505의 규정에 따라야 한다. ③ 강선, 강연선 및 강봉이 KS D 7002와 KS D 3505에 특별히 제시되지 않은 사항이 있는 경우 이들 재료가 공사시방서의 최소 규정에 적합한 것, 그리고 어느 경우에도 상기 규정된 품질 이상의 경우에만 사용할 수 있다. (7)구조용 강재, 강관, 튜브는 품질, 치수, 형상에 있어서 KS D 3503의 규격 이상이어야 하며, 특수한 경우에 책임구조기술자가 입회하여 소정의 품질 및 강도시험을 시행한 후 사용할 수 있다. (8)확대머리 전단스터드에서 확대머리의 지름은 전단스터드 지름의 $\\sqrt {10}$배 이상이어야 한다. (9)확대머리철근에서 철근 마디와 리브의 손상은 확대머리의 지압면부터 2$d_{b}$를 초과할 수 없다."
  },
  {
    "doc_id": "142001",
    "para_id": "142001_72",
    "type": "header",
    "level": 3,
    "text": "3.2.2 철근의 시험"
  },
  {
    "doc_id": "142001",
    "para_id": "142001_73",
    "type": "paragraph",
    "text": "(1) 철근의 시험은 KS B 0802 및 KS B 0804에 따라야 한다."
  },
  {
    "doc_id": "142001",
    "para_id": "142001_74",
    "type": "header",
    "level": 1,
    "text": "부록. 성능기반설계 기본 고려 사항"
  },
  {
    "doc_id": "142001",
    "para_id": "142001_75",
    "type": "header",
    "level": 1,
    "text": "1. 일반 사항"
  },
  {
    "doc_id": "142001",
    "para_id": "142001_76",
    "type": "header",
    "level": 2,
    "text": "1.1 적용 범위"
  },
  {
    "doc_id": "142001",
    "para_id": "142001_77",
    "type": "paragraph",
    "text": "(1)부록은 성능기반형으로 설계되는 콘크리트 구조물에 적용하기 위한 성능검증 방법의 개념과 원칙을 제시하는 것을 목적으로 한다. (2)발주자는 콘크리트 구조물의 안전성능, 사용성능, 내구성능 또는 환경성능을 고려하여 필요한 성능지표를 정하고 이들 각각에 대한 정량적 목표를 제시하여야 한다. (3)요구성능의 검증은 본문에 제시된 설계 방법 또는 이 부록에 제시된 원칙에 기초한 검증 방법을 이용하여 수행할 수 있다."
  },
  {
    "doc_id": "142001",
    "para_id": "142001_78",
    "type": "header",
    "level": 2,
    "text": "1.2 용어의 정의"
  },
  {
    "doc_id": "142001",
    "para_id": "142001_79",
    "type": "paragraph",
    "text": "(1) KDS 14 20 01(1.3)에 따른다."
  },
  {
    "doc_id": "142001",
    "para_id": "142001_80",
    "type": "header",
    "level": 1,
    "text": "2. 설계 원칙"
  },
  {
    "doc_id": "142001",
    "para_id": "142001_81",
    "type": "header",
    "level": 2,
    "text": "2.1 일반 사항"
  },
  {
    "doc_id": "142001",
    "para_id": "142001_82",
    "type": "paragraph",
    "text": "(1)콘크리트 구조물의 설계는 의도하는 용도에 적합한 하중조합에 근거하여야 하며, 재료 및 구조물 치수에 대한 적절한 설계값을 선택한 후 합리적인 거동이론을 적용하여 구한 구조성능이 요구되는 한계기준을 만족한다는 것을 검증하여야 한다. (2)콘크리트 구조물은 적절한 정도의 신뢰성과 경제성을 확보하면서, 목표하는 사용수명 동안 발생 가능한 모든 하중과 환경에 대하여 요구되는 구조적 안전성능, 사용성능, 내구성능과 환경성능을 갖도록 설계하여야 한다. (3)콘크리트 구조물은 필요에 따라 예측 가능한 폭발 또는 충격 등에 의해 손상되지 않도록 설계하여야 한다. (4)구조물의 성능검증에 필요한 신뢰도는 발주자가 정할 수 있으며, 적절한 안전계수와 시공 및 품질 관리를 통해 확보하여야 한다."
  },
  {
    "doc_id": "142001",
    "para_id": "142001_83",
    "type": "header",
    "level": 2,
    "text": "2.2 한계상태"
  },
  {
    "doc_id": "142001",
    "para_id": "142001_84",
    "type": "paragraph",
    "text": "(1)발주자는 안전성능, 사용성능, 내구성능, 환경성능에 관한 요구 조건을 제시할 수 있으며, 제시한 요구 조건은 콘크리트 구조물의 성능검증에서 한계기준이 될 수 있다. (2)안전성능의 한계상태는 하중, 응력 또는 변형 등과 관련되는 항목으로 표시할 수 있다. (3)사용성능의 한계상태는 응력, 균열, 변형 또는 진동 등의 항목으로 표시할 수 있다. (4)내구성능의 한계상태는 환경조건에 따른 성능저하인자가 최외측 철근까지 도달하는 시간 또는 콘크리트의 특성이 일정 수준 이하로 저하될 때까지 소요되는 시간으로 정의되는 내구수명으로 표시할 수 있다. (5)환경성능의 한계상태는 구조물을 구성하는 재료의 제조, 시공, 유지관리와 폐기 및 재활용 등의 모든 활동으로 인해 발생하는 환경저해요소 등의 항목으로 표시할 수 있다."
  },
  {
    "doc_id": "142001",
    "para_id": "142001_85",
    "type": "header",
    "level": 2,
    "text": "2.3 하중"
  },
  {
    "doc_id": "142001",
    "para_id": "142001_86",
    "type": "paragraph",
    "text": "(1)콘크리트 구조물 설계에 필요한 하중은 목표하는 수명 동안 발생 가능한 모든 하중과 환경영향을 반영하여야 한다. (2)하중의 크기 및 특성은 국가에서 정한 관련 기준에 따르는 것을 원칙으로 하되, 관련 기준에 정해져 있지 않은 하중의 크기는 통계 모델을 이용하여 결정할 수 있다. (3)발주자는 구조물의 요구성능을 고려하여 하중의 크기를 정할 수 있다. 다만, 발주자가 정한 하중 크기는 국가기준에서 정한 하중의 크기 이상이어야 한다. (4)발주자가 하중의 크기를 별도로 정할 경우 하중의 특성에 따라 강도, 지속시간, 지반조건, 재현주기, 동적특성 또는 구조물의 설계수명 및 중요도 등을 고려하여야 한다. (5)설계상황에 따라 동시에 발생 가능한 모든 하중들의 하중조합을 고려하여야 하며 하중의 변동폭과 하중조합의 특성에 따라 적절한 안전계수를 적용할 수 있다. (6)구조물과 부재에 발생하는 하중의 영향은 부록 5에 따라 산정할 수 있다."
  },
  {
    "doc_id": "142001",
    "para_id": "142001_87",
    "type": "header",
    "level": 2,
    "text": "2.4 재료"
  },
  {
    "doc_id": "142001",
    "para_id": "142001_88",
    "type": "paragraph",
    "text": "(1)설계할 때 사용하는 재료의 특성값은 통계 모델을 이용하여 분포의 평균값, 상한값, 하한값 또는 공칭값 중에서 적절한 값을 사용하여야 한다. (2)특별하게 규정되어 있지 않은 경우, 재료특성의 하한값은 하위 5%, 상한값은 상위 5%로 하여야 한다. (3)재료강도의 특성값을 공칭값으로 사용할 경우, 이 공칭값은 한국산업표준에서 정한 값 또는 이와 동등한 자격을 갖춘 시험기관에서 제공하는 자료로 정하여야 한다."
  },
  {
    "doc_id": "142001",
    "para_id": "142001_89",
    "type": "header",
    "level": 2,
    "text": "2.5 성능검증"
  },
  {
    "doc_id": "142001",
    "para_id": "142001_90",
    "type": "paragraph",
    "text": "(1)요구성능은 확률론에 근거한 신뢰성분석 또는 적절한 안전계수를 이용하여 검증할 수 있다. (2)다음과 같은 항목에 대하여 구조물의 안전성능을 검증하여야 한다. ① 구조물의 안정성을 검토할 때, 안정에 기여하는 하중영향 값은 불안정을 초래하는 하중영향 값보다 크다는 것을 검증하여야 한다. ② 구조물의 단면 또는 접합부의 파괴나 변형에 대한 한계상태를 검토할 때, 설계저항강도가 하중영향보다 크다는 것을 검증하여야 한다. ③ 2차효과에 의해 유발되는 안정성상태를 검토할 때, 작용하중에 의해 불안정한 상태가 발생하지 않는다는 것을 검증하여야 한다. ④ 피로하중에 의해 유발되는 파괴상태를 검토할 때, 반복하중에 의해 부재가 파괴되지 않는다는 것을 검증하여야 한다. (3)다음과 같은 항목에 대하여 구조물의 사용성능을 검증하여야 한다. ① 균열에 대한 사용성능은 휨모멘트에 의한 영향뿐만 아니라 전단력에 의한 영향도 고려하여 검증하여야 한다. ② 변형에 대한 사용성능은 부재의 변형뿐만 아니라 구조 시스템의 변형도 고려하여 검증하여야 한다. ③ 진동에 대한 사용성능은 요구 조건으로 제시된 고유진동수 또는 진동가속도에 대하여 검증하여야 한다. (4)다음과 같은 항목에 대하여 구조물의 내구성능을 검증하여야 한다. ① 내구성능은 구조물이 위치하는 장소의 성능저하인자들을 평가하여 가장 지배적인 성능저하인자에 대하여 검증하는 것을 원칙으로 한다. ② 내구성능은 성능저하인자에 의한 철근부식 개시시점까지 기간이 요구성능으로 제시된 내구연한보다 길다는 것을 검증하여야 한다. ③ 내구성능검증에서 복합열화를 무시할 수 없을 경우에는 이를 고려하여야 한다. (5)다음과 같은 항목에 대하여 구조물의 환경성능을 검증하여야 한다. ① 구조물을 구성하는 재료를 제조할 때부터 구조물을 해체 및 재활용하는 전 단계에 걸쳐 투입되는 모든 재료 및 활동으로 인해 발생하는 환경저해요소가 국가 또는 발주자가 요구하는 환경성능 한계기준을 초과하지 않도록 하여야 한다. ② 환경성능검증은 대기오염, 수질 및 토질오염, 작업환경에 영향을 미치는 인자에 대하여 수행하여야 한다."
  },
  {
    "doc_id": "142001",
    "para_id": "142001_91",
    "type": "header",
    "level": 1,
    "text": "3. 재료"
  },
  {
    "doc_id": "142001",
    "para_id": "142001_92",
    "type": "header",
    "level": 2,
    "text": "3.1 일반 사항"
  },
  {
    "doc_id": "142001",
    "para_id": "142001_93",
    "type": "paragraph",
    "text": "(1)해석과 설계에 고려하여야 하는 재료특성은 다음과 같은 사항을 포함하여야 한다. ① 압축, 인장, 전단 특성 ② 탄성계수 ③ 크리프, 릴랙세이션, 건조 및 자기수축 등의 시간 의존적 특성 ④ 수밀성과 확산계수 등의 환경하중과 관련되는 특성 ⑤ 열팽창계수 등의 열적 특성 ⑥ 응력-변형률 관계 (2)재료의 특성값은 적절한 시험 또는 신뢰성 있는 모델식을 사용하여 결정하여야 한다. (3)콘크리트 부재 및 구조물의 성능검증을 위하여 콘크리트의 재령 영향이 고려되어야 하는 경우에는 신뢰성 있는 모델이나 해석 방법을 사용하여 그 영향을 반영하여야 한다."
  },
  {
    "doc_id": "142001",
    "para_id": "142001_94",
    "type": "header",
    "level": 2,
    "text": "3.2 콘크리트 압축강도"
  },
  {
    "doc_id": "142001",
    "para_id": "142001_95",
    "type": "paragraph",
    "text": "(1)콘크리트의 설계기준압축강도는 1축압축강도를 기준으로 하며, 콘크리트 부재 및 구조물의 성능검증에는 1축압축강도 이외에 2축 및 3축 응력상태를 고려한 유효압축강도 모델을 사용할 수 있다. (2)설계기준압축강도는 재령 28일에 평가한 표준원주공시체 압축강도 분포의 하위 5%로 나타내는 것을 원칙으로 한다."
  },
  {
    "doc_id": "142001",
    "para_id": "142001_96",
    "type": "header",
    "level": 2,
    "text": "3.3 콘크리트 인장강도"
  },
  {
    "doc_id": "142001",
    "para_id": "142001_97",
    "type": "paragraph",
    "text": "(1)콘크리트의 인장강도는 시험 또는 신뢰성 있는 모델식을 사용하여 결정하여야 한다. (2)콘크리트 부재의 사용성능검증을 위한 콘크리트의 설계기준인장강도는 분포의 하위 5%로 나타내는 것을 원칙으로 한다. (3)콘크리트 휨부재의 최소 철근비 산정을 위한 콘크리트의 설계기준인장강도는 분포의 상위 5%로 나타내는 것을 원칙으로 한다. (4)콘크리트의 휨인장강도는 KS F 2408의 규정에 따라 구하거나 신뢰성 있는 모델식을 사용하여 결정하여야 한다."
  },
  {
    "doc_id": "142001",
    "para_id": "142001_98",
    "type": "header",
    "level": 2,
    "text": "3.4 콘크리트 탄성변형"
  },
  {
    "doc_id": "142001",
    "para_id": "142001_99",
    "type": "paragraph",
    "text": "(1)콘크리트의 탄성계수는 KS F 2438의 규정에 따라 구하거나 신뢰성 있는 모델식을 사용하여 결정하여야 한다. (2)콘크리트 포아송비와 열팽창계수는 시험 또는 신뢰성 있는 모델을 사용하여 결정하여야 한다."
  },
  {
    "doc_id": "142001",
    "para_id": "142001_100",
    "type": "header",
    "level": 2,
    "text": "3.5 콘크리트의 크리프 및 수축"
  },
  {
    "doc_id": "142001",
    "para_id": "142001_101",
    "type": "paragraph",
    "text": "(1)콘크리트의 크리프 및 수축의 변형률은 주변 대기습도, 부재의 치수 및 콘크리트 구성성분의 영향과 하중이 최초로 재하될 때의 콘크리트 성숙도와 하중의 크기 및 재하기간의 영향을 반영하여 결정하여야 한다. (2)콘크리트의 전체 수축량을 계산하고자 할 경우에는 수축변형률 이외에도 자기수축변형률을 고려하여야 한다."
  },
  {
    "doc_id": "142001",
    "para_id": "142001_102",
    "type": "header",
    "level": 2,
    "text": "3.6 콘크리트 응력-변형률 관계"
  },
  {
    "doc_id": "142001",
    "para_id": "142001_103",
    "type": "paragraph",
    "text": "(1)콘크리트의 응력-변형률 관계는 최대 강도, 최대 강도에 해당하는 변형률, 최대 강도 이후의 강도저하, 최대 변형률 등의 응력-변형률 상태를 잘 나타낼 수 있어야 한다."
  },
  {
    "doc_id": "142001",
    "para_id": "142001_104",
    "type": "header",
    "level": 2,
    "text": "3.7 철근"
  },
  {
    "doc_id": "142001",
    "para_id": "142001_105",
    "type": "paragraph",
    "text": "(1)한국산업표준에서 규정한 철근의 사용을 원칙으로 하되, 그 이외의 철근을 사용할 경우에는 한국산업표준에서 정한 시험 방법에 따라 설계할 때 가정된 역학적 성능을 검증하여야 한다. (2)철근은 연성과 용접성 및 굽힘성을 적절히 확보하여야 한다."
  },
  {
    "doc_id": "142001",
    "para_id": "142001_106",
    "type": "header",
    "level": 2,
    "text": "3.8 긴장재"
  },
  {
    "doc_id": "142001",
    "para_id": "142001_107",
    "type": "paragraph",
    "text": "(1)프리스트레스트콘크리트는 긴장재로 강선, 강봉 또는 강연선을 사용할 수 있다. (2)프리스트레싱 긴장재는 성능을 저하시킬 수 있는 결함이 없어야 하고 응력 부식이 일어날 가능성이 충분히 낮은 수준이어야 한다. (3)프리스트레싱 긴장재는 한국산업표준에서 요구하는 연성 및 피로강도를 가져야 한다. (4)한국산업표준에서 규정한 긴장재의 사용을 원칙으로 하되, 그 이외의 긴장재를 사용할 경우에는 관련 시험 방법에 따라 설계할 때 가정된 역학적 성능을 검증하여야 한다."
  },
  {
    "doc_id": "142001",
    "para_id": "142001_108",
    "type": "header",
    "level": 1,
    "text": "4. 기본구조요소"
  },
  {
    "doc_id": "142001",
    "para_id": "142001_109",
    "type": "header",
    "level": 2,
    "text": "4.1 일반 사항"
  },
  {
    "doc_id": "142001",
    "para_id": "142001_110",
    "type": "paragraph",
    "text": "(1)이 장은 철근콘크리트의 부분요소 또는 부재의 역학적 모델에 관한 것으로 구조해석 및 성능검증에 적용할 수 있다. (2)콘크리트 부재는 응력의 분포상태를 고려하여 1축요소와 2축 및 다축요소로 이상화할 수 있다. (3)콘크리트 구조물은 거동을 지배하는 응력과 변형률을 고려하여 기본구조요소의 조합으로 이상화할 수 있다. (4)휨부재의 모멘트는 1축압축요소와 1축인장요소의 짝힘으로 전달된다고 이상화할 수 있다."
  },
  {
    "doc_id": "142001",
    "para_id": "142001_111",
    "type": "header",
    "level": 2,
    "text": "4.2 1축콘크리트요소"
  },
  {
    "doc_id": "142001",
    "para_id": "142001_112",
    "type": "paragraph",
    "text": "(1)주변의 응력조건을 고려하여 콘크리트의 압축과 인장력에 대한 응력-변형률 관계를 정의하여야 한다. (2)휨부재 1축압축요소의 설계를 위해 단순한 형태의 콘크리트 응력-변형률 관계를 사용할 수 있다. (3)필요할 경우, 설계기준압축강도는 장기하중의 효과를 고려하여야 한다. (4)콘크리트의 변형률 연화현상을 고려할 수 있다."
  },
  {
    "doc_id": "142001",
    "para_id": "142001_113",
    "type": "header",
    "level": 2,
    "text": "4.3 철근 및 긴장재 요소"
  },
  {
    "doc_id": "142001",
    "para_id": "142001_114",
    "type": "paragraph",
    "text": "(1)철근의 응력-변형률 관계는 탄성-완전소성 관계로 이상화할 수 있다. (2)긴장재와 같이 항복점이 명확하지 않은 경우에는 비선형 관계를 적절히 나타낼 수 있도록 응력-변형률 관계를 정의하여야 한다."
  },
  {
    "doc_id": "142001",
    "para_id": "142001_115",
    "type": "header",
    "level": 2,
    "text": "4.4 부착"
  },
  {
    "doc_id": "142001",
    "para_id": "142001_116",
    "type": "paragraph",
    "text": "(1)철근콘크리트 부재의 단면해석에서 철근과 콘크리트 사이의 부착 응력-미끄러짐 관계를 적용할 수 있다. (2)철근과 콘크리트 사이의 부착 응력-미끄러짐 관계는 철근의 표면 특성과 구속응력상태를 고려한 신뢰성 있는 모델을 사용할 수 있다. (3)철근의 부착응력 특성을 고려하여 1축인장요소의 응력-변형률 관계를 정할 수 있다. (4)철근과 콘크리트의 부착으로 인한 인장증강효과를 고려한 콘크리트의 인장응력과 변형관계식을 사용할 수 있다."
  },
  {
    "doc_id": "142001",
    "para_id": "142001_117",
    "type": "header",
    "level": 2,
    "text": "4.5 균열 발생 이전의 2축응력요소"
  },
  {
    "doc_id": "142001",
    "para_id": "142001_118",
    "type": "paragraph",
    "text": "(1)탄성연속체 역학에 근거하여 2축응력요소의 응력-변형률 관계를 설정할 수 있다. (2)2축응력요소의 응력-변형률 관계는 다축응력상태의 효과를 고려하여 정하여야 한다."
  },
  {
    "doc_id": "142001",
    "para_id": "142001_119",
    "type": "header",
    "level": 2,
    "text": "4.6 균열 발생 이후 2축응력요소"
  },
  {
    "doc_id": "142001",
    "para_id": "142001_120",
    "type": "paragraph",
    "text": "(1)균열 발생 이후 콘크리트는 주로 압축응력을 전달하는 요소로 이상화할 수 있다. (2)2축요소의 거동은 평균 응력에 대한 평형조건과 평균 변형률에 대한 적합조건을 만족하여야 한다. (3)콘크리트요소의 응력-변형률 관계는 주변 응력과 변형을 고려하여 정하여야 한다. (4)콘크리트의 경사 압축응력대의 수직/수평 기울기는 주인장철근 방향에 대하여 1/2에서 2까지 가정할 수 있다."
  },
  {
    "doc_id": "142001",
    "para_id": "142001_121",
    "type": "header",
    "level": 2,
    "text": "4.7 2축응력요소의 강도"
  },
  {
    "doc_id": "142001",
    "para_id": "142001_122",
    "type": "paragraph",
    "text": "(1)압축강도는 철근과 콘크리트 강도의 합으로 표현하여야 한다. (2)필요할 경우 콘크리트의 인장강도 영향을 고려할 수 있다. (3)전단강도는 부재에 작용하는 인장응력과 압축응력의 효과, 철근항복과 콘크리트의 압축파괴를 고려하여 결정하여야 한다."
  },
  {
    "doc_id": "142001",
    "para_id": "142001_123",
    "type": "header",
    "level": 2,
    "text": "4.8 겹판요소"
  },
  {
    "doc_id": "142001",
    "para_id": "142001_124",
    "type": "paragraph",
    "text": "(1)판부재에 면내력과 함께 비틀림모멘트, 휨모멘트 또는 면외전단력이 작용하는 경우, 판부재는 2축응력요소가 상, 하면에 각각 작용하는 겹판으로 이상화할 수 있다. (2)판부재에 면외전단력이 작용하는 경우, 2축응력이 작용하는 3개의 판요소로 이상화할 수 있으며 이상화된 상․하 판요소는 휨모멘트와 비틀림모멘트에 대한 응력을 전달하고 가운데 판요소는 면외전단력을 전달한다고 간주할 수 있다."
  },
  {
    "doc_id": "142001",
    "para_id": "142001_125",
    "type": "header",
    "level": 1,
    "text": "5. 구조해석"
  },
  {
    "doc_id": "142001",
    "para_id": "142001_126",
    "type": "header",
    "level": 2,
    "text": "5.1 일반 사항"
  },
  {
    "doc_id": "142001",
    "para_id": "142001_127",
    "type": "paragraph",
    "text": "(1)구조해석을 위한 구조물 및 부재의 크기, 재료, 하중, 경계조건은 구조물의 현황과 가까운 조건을 사용하여야 한다. 다만, 정확한 현황을 알 수 없는 경우에는 안전측이 되도록 하여야 한다. (2)구조해석은 재료의 특성, 2차효과, 장기효과, 온도 변화, 시공 편차, 시공단계 효과, 영구 변형, 지반의 영향 등을 고려하여 수행하여야 한다."
  },
  {
    "doc_id": "142001",
    "para_id": "142001_128",
    "type": "header",
    "level": 2,
    "text": "5.2 구조물 및 부재의 이상화"
  },
  {
    "doc_id": "142001",
    "para_id": "142001_129",
    "type": "paragraph",
    "text": "(1)재료의 특성과 구조요소의 구성은 부록.3과 부록.4를 따라야 한다. (2)구조 부재의 특성과 기능에 따라 보, 기둥, 벽, 슬래브, 아치, 쉘 등으로 구분하고 이들의 조합이 구조물의 거동을 적절히 묘사할 수 있도록 이상화하여 구조해석을 수행하여야 한다. (3)선형의 변형률 분포 가정이 유효하지 않은 영역에 대해서는 추가 부분해석을 사용할 수 있다. 이때 부분해석 모델은 영역의 경계면에서 부분영역이 속한 전체 구조물의 힘의 평형조건과 변형의 적합조건을 만족하여야 한다. (4)깊은보, 깊은 연결보, 낮은 기둥, 낮은 벽, 말뚝캡 등 상대적으로 전단경간이 작은 부재에 대해서는 유한요소해석 또는 스트럿-타이 모델해석을 사용하여야 한다."
  },
  {
    "doc_id": "142001",
    "para_id": "142001_130",
    "type": "header",
    "level": 2,
    "text": "5.3 선형탄성 해석"
  },
  {
    "doc_id": "142001",
    "para_id": "142001_131",
    "type": "paragraph",
    "text": "(1)탄성이론에 근거한 골조 및 부재의 선형해석은 사용한계상태 및 극한한계상태 설계에 모두 사용할 수 있다. (2)균열이 예상되는 경우에는 균열의 영향을 고려한 단면의 유효강성을 사용하여야 한다. (3)하중의 지속효과에 의한 콘크리트의 장기변형을 무시할 수 없을 경우에는 크리프의 영향을 포함하는 균열단면에 대한 감소된 강성을 사용하여야 한다. (4)극한한계상태설계에 선형탄성 유한요소해석을 사용할 경우, 응력 또는 내력은 재분배의 영향을 고려하여 적절한 크기의 영역에 대하여 평균값을 사용하여 설계할 수 있다."
  },
  {
    "doc_id": "142001",
    "para_id": "142001_132",
    "type": "header",
    "level": 2,
    "text": "5.4 휨모멘트 재분배를 고려한 선형탄성 해석"
  },
  {
    "doc_id": "142001",
    "para_id": "142001_133",
    "type": "paragraph",
    "text": "(1)제한된 휨모멘트 재분배를 고려한 선형탄성 해석은 극한한계상태의 구조 부재 해석에 적용할 수 있다. (2)선형탄성 해석을 사용하여 구한 극한한계상태의 휨모멘트를 재분배하는 경우, 재분배된 휨모멘트는 구조물에 작용하는 하중과 정적평형조건을 만족시켜야 한다. (3)선형탄성해석에 대한 제한된 휨모멘트 재분배는 중력하중 또는 지진하중을 받는 연속보와 슬래브에 적용할 수 있다. 다만, 재분배에 필요한 부재의 비탄성 회전변형능력에 대하여 검증하여야 한다. (4)프리스트레스트콘크리트 골조의 모서리와 같이 부재의 비탄성 회전변형능력을 정확히 검증하지 못하는 곳에는 선형탄성 해석에 의한 휨모멘트 재분배를 허용할 수 없다. (5)기둥의 경우 휨모멘트 재분배를 허용할 수 없다."
  },
  {
    "doc_id": "142001",
    "para_id": "142001_134",
    "type": "header",
    "level": 2,
    "text": "5.5 선형비탄성 해석"
  },
  {
    "doc_id": "142001",
    "para_id": "142001_135",
    "type": "paragraph",
    "text": "(1)극한한계상태에서 비탄성 거동을 보이는 구조물 및 부재에 대하여 하중의 재분배와 소성변형을 평가하는 구조해석 방법으로 선형비탄성 해석을 사용할 수 있다. (2)구조물 또는 부재의 예상되는 변형거동과 비탄성변형의 크기에 적합하도록 구조요소의 할선강성을 가정하여야 하며, 이 할선강성은 탄성강성 이하이어야 한다. (3)할선강성을 갖는 구조모델에 대한 선형해석을 수행하여 재분배된 부재 내력에 대하여 설계하며, 이때 각 부재의 비탄성변형은 해당 부재의 비탄성변형능력을 초과할 수 없다. (4)과도한 부재의 비탄성변형능력이 요구되는 경우에는 할선강성을 증가시켜서 재해석을 수행하여야 한다."
  },
  {
    "doc_id": "142001",
    "para_id": "142001_136",
    "type": "header",
    "level": 2,
    "text": "5.6 소성해석"
  },
  {
    "doc_id": "142001",
    "para_id": "142001_137",
    "type": "paragraph",
    "text": "(1)극한한계상태의 설계와 검증을 위하여 소성해석 방법을 사용할 수 있다. (2)위험단면에서는 의도한 소성기구가 형성되기에 충분하도록 연성을 확보하여야 한다. 극한한계상태의 구조해석 방법으로 소성해석을 사용하기 위해서는 계산된 부재의 회전변형이 허용소성회전변형보다 크지 않아야 한다. (3)정적하중이 지배적인 경우, 하중은 단조증가하는 것으로 가정할 수 있다."
  },
  {
    "doc_id": "142001",
    "para_id": "142001_138",
    "type": "header",
    "level": 2,
    "text": "5.7 비선형해석"
  },
  {
    "doc_id": "142001",
    "para_id": "142001_139",
    "type": "paragraph",
    "text": "(1)힘의 평형조건 및 변형의 적합조건을 만족하고 재료의 비선형거동을 적절하게 고려한 경우, 비선형해석 방법은 극한 및 사용한계상태에 대한 설계에 적용할 수 있다. 기하학적 비선형효과를 고려해야 하는 경우에는 2차효과를 포함하여야 한다. (2)극한한계상태의 경우, 위험단면이 비선형해석에 의해 구한 비탄성변형을 견딜 수 있는 회전변형능력을 확보하고 있는지에 대하여 검토하여야 한다. (3)독립된 하중에 대한 비선형해석 결과를 중첩할 수 없다. 정적재하가 지배적인 구조물의 경우, 하중은 단조증가하는 것으로 가정할 수 있다. (4)비선형해석을 사용하는 경우에는 실제 부재강성을 나타내면서도 파괴의 불확실성을 고려할 수 있는 재료특성값을 사용하여야 한다."
  },
  {
    "doc_id": "142001",
    "para_id": "142001_140",
    "type": "header",
    "level": 2,
    "text": "5.8 부재의 허용소성회전변형"
  },
  {
    "doc_id": "142001",
    "para_id": "142001_141",
    "type": "paragraph",
    "text": "(1)단조하중에 저항하는 연속보와 슬래브의 허용소성회전변형은 부재의 압축대 콘크리트에서 인장철근의 항복보다 먼저 휨압축파괴가 발생하지 않도록 결정하여야 한다. (2)지진에 저항하는 부재의 회전변형능력은 압축대 콘크리트의 휨압축파괴 및 전단파괴, 철근의 좌굴, 철근의 파단 등 주기하중에 의해 발생할 수 있는 다양한 파괴양상이 고려되어야 한다. 지진에 저항하는 부재의 회전변형능력은 단조하중에 의한 부재의 회전변형능력을 초과할 수 없다."
  },
  {
    "doc_id": "142001",
    "para_id": "142001_142",
    "type": "header",
    "level": 2,
    "text": "5.9 2차 효과"
  },
  {
    "doc_id": "142001",
    "para_id": "142001_143",
    "type": "paragraph",
    "text": "(1)구조적 거동이 2차효과에 의하여 현저하게 영향을 받는 구조물 또는 부재에서는 2차효과를 고려하여 부재의 휨모멘트 확대와 구조물의 안전성을 검토하여야 한다. (2)2차해석은 구조물의 하중조건, 지지조건에 맞는 변형형상을 고려하여야 하고, 변형된 상태에 대한 힘의 평형조건과 저항성능을 검증하여야 한다."
  },
  {
    "doc_id": "142001",
    "para_id": "142001_144",
    "type": "header",
    "level": 2,
    "text": "5.10 프리스트레스트콘크리트 부재의 해석"
  },
  {
    "doc_id": "142001",
    "para_id": "142001_145",
    "type": "paragraph",
    "text": "(1)초기 프리스트레스를 도입할 때 긴장재에는 비탄성 변형이 발생하지 말아야 하고, 프리스트레스 정착 장치 위치에서 국부적인 콘크리트의 파쇄나 쪼갬 등 취성파괴가 발생되지 않아야 한다. (2)프리스트레스트콘크리트 부재를 해석할 때, 콘크리트 탄성변형, 긴장재의 마찰, 정착 장치 등에 의한 순간손실과 지속하중에 의한 콘크리트 장기변형 및 긴장재의 응력이완에 의한 장기손실을 고려하여야 한다. (3)휨모멘트의 재분배를 고려하기 이전에 프리스트레싱에 의한 1차 및 2차 효과에 의한 선형해석이 수행되어야 한다. (4)소성 및 비선형해석에서 회전 및 회전능력을 검토할 때, 프리스트레싱의 2차 효과를 고려하여야 한다."
  },
  {
    "doc_id": "142001",
    "para_id": "142001_146",
    "type": "header",
    "level": 1,
    "text": "6. 안전성능검증－휨모멘트 및 축력"
  },
  {
    "doc_id": "142001",
    "para_id": "142001_147",
    "type": "header",
    "level": 2,
    "text": "6.1 일반 사항"
  },
  {
    "doc_id": "142001",
    "para_id": "142001_148",
    "type": "paragraph",
    "text": "(1)이 장의 규정은 휨부재 또는 압축부재에서 평면유지 가정이 유효한 영역의 성능평가와 설계에 적용하여야 한다. 평면유지 가정이 유효하지 않은 영역의 설계는 스트럿-타이 설계법을 적용하여야 한다. (2)이 장의 규정은 철근 또는 긴장재가 콘크리트에 부착된 부재에 적용하여야 한다."
  },
  {
    "doc_id": "142001",
    "para_id": "142001_149",
    "type": "header",
    "level": 2,
    "text": "6.2 한계상태의 설정"
  },
  {
    "doc_id": "142001",
    "para_id": "142001_150",
    "type": "paragraph",
    "text": "(1)발주자는 다음 사항에 대한 한계상태를 결정할 수 있다. ① 콘크리트의 응력 또는 변형률 한계 ② 철근의 응력 또는 변형률 한계 ③ 부재의 연성 및 변형 한계"
  },
  {
    "doc_id": "142001",
    "para_id": "142001_151",
    "type": "header",
    "level": 2,
    "text": "6.3 성능검증"
  },
  {
    "doc_id": "142001",
    "para_id": "142001_152",
    "type": "paragraph",
    "text": "(1)부재의 안전성능은 부록 4의 규정에 따라 제시되는 기본구조요소 모델과 재료의 성질을 반영한 역학 이론에 근거한 해석 모델 또는 실험에 의하여 검증하여야 한다. (2)부재의 응력균일영역에서는 부록 4의 규정에 따라 제시되는 기본구조요소 모델로 단면을 구분하는 대신에, 단면 내의 변형률 분포를 고려한 단면해석 모델을 적용할 수 있다. (3)안전성능의 검증에서 부록 5.4에 따른 휨모멘트 재분배를 고려한 선형탄성 해석, 부록 5.5에 따른 선형비탄성 해석, 부록 5.6에 따른 소성해석, 부록 5.7에 따른 비선형해석을 적용한 경우에는 회전각을 한계값으로 하여 회전변형능력을 검증하여야 한다. (4)부재의 응력균일영역에서는 다음의 가정을 적용한 단면해석모델을 통하여 성능을 평가할 수 있다. ① 변형 전의 중립축에 수직한 평면은 하중에 의해 변형된 후에도 평면을 유지한다. ② 콘크리트에 부착된 철근과 프리스트레싱 긴장재의 변형률은 인장상태나 압축상태에서 주변 콘크리트의 변형률과 같다. ③ 균열이 발생된 콘크리트의 인장강도는 무시할 수 있다. ④ 휨모멘트와 축력을 받는 부재 단면의 콘크리트의 압축응력 분포는 부록 3.6의 규정에 따라 설정된 응력-변형률 관계를 따른다고 간주한다. ⑤ 철근과 긴장재는 부록 3.7의 규정에 따라 설정된 응력-변형률 관계를 따른다고 간주한다."
  },
  {
    "doc_id": "142001",
    "para_id": "142001_153",
    "type": "paragraph",
    "text": "(5)부재의 회전변형능력은 단면해석모델을 적용한 모멘트-곡률 해석에 따라 극한한계상태의 곡률분포를 얻은 후 소성힌지부의 곡률을 적분하여 구할 수 있으며, 이때 부록.5.8에 제시된 파괴거동을 고려하여야 한다. (6)부재의 단면강도는 단면해석 모델을 적용한 모멘트-곡률 관계에 의해 구한 극한한계상태에 대한 강도로 결정하거나, 극한한계상태의 응력분포를 대상으로 한 단면강도해석으로 구할 수 있다."
  },
  {
    "doc_id": "142001",
    "para_id": "142001_154",
    "type": "header",
    "level": 1,
    "text": "7. 안전성능검증-전단력 및 비틀림모멘트"
  },
  {
    "doc_id": "142001",
    "para_id": "142001_155",
    "type": "header",
    "level": 2,
    "text": "7.1 일반 사항"
  },
  {
    "doc_id": "142001",
    "para_id": "142001_156",
    "type": "paragraph",
    "text": "(1)이 장은 전단력과 비틀림모멘트를 받는 선부재, 면부재와 전단마찰이 작용하는 부재에 대한 성능검증에 적용한다."
  },
  {
    "doc_id": "142001",
    "para_id": "142001_157",
    "type": "header",
    "level": 2,
    "text": "7.2 한계상태의 설정"
  },
  {
    "doc_id": "142001",
    "para_id": "142001_158",
    "type": "paragraph",
    "text": "(1)발주자는 다음 사항에 대한 한계상태를 결정할 수 있다. ① 콘크리트의 응력 또는 변형률 한계 ② 철근의 응력 또는 변형률 한계 ③ 부재의 연성 및 변형 한계"
  },
  {
    "doc_id": "142001",
    "para_id": "142001_159",
    "type": "header",
    "level": 2,
    "text": "7.3 성능검증-전단철근이 없는 선부재"
  },
  {
    "doc_id": "142001",
    "para_id": "142001_160",
    "type": "paragraph",
    "text": "(1)전단철근이 없는 선부재의 전단강도는 콘크리트의 인장강도를 이용하여 결정할 수 있으며 정밀한 방법이 요구될 경우 콘크리트의 인장강도, 전단경간비, 주철근의 양, 크기효과를 고려하여 계산할 수 있다. (2)프리스트레스트콘크리트 부재의 전단강도를 계산할 때 복부의 주인장 응력이 콘크리트의 인장강도를 초과할 수 없다."
  },
  {
    "doc_id": "142001",
    "para_id": "142001_161",
    "type": "header",
    "level": 2,
    "text": "7.4 성능검증-전단철근이 있는 선부재"
  },
  {
    "doc_id": "142001",
    "para_id": "142001_162",
    "type": "paragraph",
    "text": "(1)전단철근이 있는 부재의 전단강도는 부록 4에서 제시하는 기본구조요소를 근거하여 각 부재를 트러스 모델로 이상화하여 계산할 수 있다. (2)설계전단강도는 스터럽 내력, 휨철근의 부착 내력, 복부 경사콘크리트의 내력 중에서 최솟값으로 한다. 이때 복부 경사콘크리트의 내력은 안전율을 고려하여 제한된 값을 사용하여 계산하여야 한다. (3)전단철근이 있는 부재는 복부콘크리트의 압축파괴가 전단보강철근이 항복한 이후에 일어나도록 설계하여야 한다. (4)콘크리트압축대의 경사각도는 정밀한 방법으로 계산할 수 있다. (5)주철근의 양을 결정할 때는 콘크리트압축대의 경사각도에 따라 추가로 발생하는 인장력을 고려하여 설계하여야 한다. (6)전단보강철근의 상세나 최소 전단보강철근량 및 최대 전단보강철근량은 검증된 방법에 의하여 결정할 수 있다. (7)전단력을 받는 부재의 사용한계상태를 검증할 때에는 사용하중에 의하여 계산한 전단균열의 폭이 요구한계값 이상이 되지 않도록 설계하여야 한다. (8)전단력을 받는 부재의 극한한계상태를 검증할 때에는 극한하중에 의하여 계산한 전단력 또는 전단응력이 부재 단면 또는 재료의 전단강도를 초과하지 않도록 설계하여야 한다."
  },
  {
    "doc_id": "142001",
    "para_id": "142001_163",
    "type": "header",
    "level": 2,
    "text": "7.5 성능검증-선부재의 비틀림"
  },
  {
    "doc_id": "142001",
    "para_id": "142001_164",
    "type": "paragraph",
    "text": "(1)비틀림철근이 있는 부재의 비틀림강도는 부록 4에서 제시하는 기본구조요소를 근거하여 부재를 입체트러스 모델과 박벽관 모델로 이상화하여 계산할 수 있다. (2)설계비틀림강도는 부재축과 직각방향의 비틀림내력, 부재축방향의 비틀림내력, 복부 경사콘크리트의 내력 중에서 최솟값으로 한다. 이때 복부 경사콘크리트의 내력은 안전율을 고려하여 제한된 값을 사용하여 계산하여야 한다. (3)비틀림을 받는 부재는 비틀림보강철근이 항복한 이후에 복부 경사콘크리트가 압축파괴되도록 설계하여야 한다. (4)전단흐름 내부의 면적은 부재의 변형이 커진 후의 콘크리트 탈락 여부를 고려하여 계산하여야 한다. (5)부재에 비틀림모멘트와 함께 전단력, 휨모멘트 또는 축력 등과 같은 하중이 동시에 작용할 경우 복합하중이 부재에 미치는 영향을 고려하여 설계비틀림강도를 계산하여야 한다. (6)필요한 경우, 부정정비틀림내력은 균열에 의한 비틀림모멘트 재분배 효과를 고려하여 계산하여야 한다. (7)비틀림 보강철근의 상세나 최소 비틀림 보강철근량 및 최대 비틀림 보강철근량은 검증된 방법에 의하여 정할 수 있다. (8)비틀림을 받는 부재의 사용한계상태를 검증할 때에는 사용하중에 의하여 계산한 비틀림균열의 폭이 요구한계상태 이상이 되지 않도록 설계하여야 한다. (9)비틀림을 받는 부재의 극한한계상태를 검증할 때에는 극한하중에 의하여 계산한 비틀림모멘트 또는 비틀림 응력이 부재 단면 및 재료의 설계비틀림강도를 초과하지 않도록 설계하여야 한다."
  },
  {
    "doc_id": "142001",
    "para_id": "142001_165",
    "type": "header",
    "level": 2,
    "text": "7.6 성능검증-슬래브의 2방향전단"
  },
  {
    "doc_id": "142001",
    "para_id": "142001_166",
    "type": "paragraph",
    "text": "(1)슬래브와 기초판 등 면부재의 받침부나 집중하중영역에 대하여 2방향전단을 검토하여야 한다. (2)2방향전단에 관한 설계강도는 콘크리트와 전단보강철근의 전단기여도를 고려하여 계산하며 개구부의 영향을 고려하여야 한다. (3)프리스트레스트콘크리트 슬래브에서 콘크리트의 2방향전단강도는 유효프리스트레스트 힘의 영향을 고려하여 증가시킬 수 있다. (4)전단보강재에 의한 2방향전단강도는 부록.4에서 제시하는 기본구조요소를 근거하여 트러스 모델로 이상화할 수 있다. (5)연직하중, 풍하중, 지진하중 또는 기타 횡하중으로 인하여 기둥에 휨모멘트가 전달되는 경우에는 2방향전단력과 함께 휨모멘트의 영향을 고려하여야 한다."
  },
  {
    "doc_id": "142001",
    "para_id": "142001_167",
    "type": "header",
    "level": 2,
    "text": "7.7 성능검증-면내응력 부재"
  },
  {
    "doc_id": "142001",
    "para_id": "142001_168",
    "type": "paragraph",
    "text": "(1)면내응력 부재는 압축, 인장 및 전단응력의 크기를 고려하여 철근을 배치하여야 한다. (2)철근이 있는 면내응력 부재의 설계전단강도는 부록 4에서 제시하는 기본구조요소를 근거하여 트러스 모델로 이상화할 수 있다. (3)설계전단강도는 양방향 철근의 내력, 복부 경사콘크리트의 내력 중에서 최솟값으로 한다. 이때 복부 경사콘크리트의 내력은 인장균열을 고려하여 감소된 값을 사용하여 계산하여야 한다. (4)경사콘크리트 압축대의 각도는 정밀한 방법으로 계산할 수 있다. (5)면내응력 부재의 사용한계상태를 검증할 때에는 사용하중에 의하여 계산한 균열의 폭이 요구한계상태 이상이 되지 않도록 설계하여야 한다. (6)면부재의 극한한계상태를 검증할 때에는 극한하중에 의하여 계산한 하중 또는 응력이 부재 및 재료의 설계강도를 초과하지 않도록 설계하여야 한다."
  },
  {
    "doc_id": "142001",
    "para_id": "142001_169",
    "type": "header",
    "level": 2,
    "text": "7.8 성능검증-벽체"
  },
  {
    "doc_id": "142001",
    "para_id": "142001_170",
    "type": "paragraph",
    "text": "(1)콘크리트의 설계전단강도는 부록 7.4에 규정된 선부재의 콘크리트 전단강도를 사용할 수 있다. 다만, 정밀한 방법으로 계산할 때에는 축력과 휨모멘트의 영향을 고려하여 콘크리트의 설계전단강도를 계산할 수 있다. (2)스트럿-타이 모델을 이용하여 벽체의 성능을 검증할 때는 벽체의 형상비에 따른 면내응력을 고려하여 설계전단강도를 결정하여야 한다. (3)전단철근이 있는 부재의 설계전단강도는 부록 4에서 제시하는 기본구조요소를 근거하여 트러스 모델로 이상화할 수 있다. (4)전단보강철근의 상세, 최소 전단보강철근량, 철근의 최대 간격은 검증된 방법에 의해 정할 수 있다."
  },
  {
    "doc_id": "142001",
    "para_id": "142001_171",
    "type": "header",
    "level": 2,
    "text": "7.9 성능검증-전단마찰"
  },
  {
    "doc_id": "142001",
    "para_id": "142001_172",
    "type": "paragraph",
    "text": "(1)전단마찰철근이 있는 부재의 전단강도는 마찰계수를 고려한 힘의 평형에 의하여 계산하여야 하며, 이 값은 규정된 값을 초과할 수 없다. (2)마찰계수는 콘크리트의 표면 상태와 콘크리트의 종류에 따라서 다르게 적용하여야 한다."
  },
  {
    "doc_id": "142001",
    "para_id": "142001_173",
    "type": "header",
    "level": 1,
    "text": "8. 사용성능검증"
  },
  {
    "doc_id": "142001",
    "para_id": "142001_174",
    "type": "header",
    "level": 2,
    "text": "8.1 일반 사항"
  },
  {
    "doc_id": "142001",
    "para_id": "142001_175",
    "type": "paragraph",
    "text": "(1)구조물과 구조 부재는 예측 가능한 모든 사용하중조합에서 적절하게 기능을 유지할 수 있도록 사용성능을 확보하여야 한다. (2)발주자는 구조물 및 구조 부재의 사용한계상태를 정할 수 있다. 이때 사용한계상태는 구조물과 구조 부재의 종류와 기능에 따라 응력, 균열폭, 처짐, 진동 등에 관한 항으로 나타낼 수 있다. (3)사용한계는 구조물의 사용목적과 노출환경 등을 고려하여 결정하여야 한다."
  },
  {
    "doc_id": "142001",
    "para_id": "142001_176",
    "type": "header",
    "level": 2,
    "text": "8.2 사용한계상태 설정"
  },
  {
    "doc_id": "142001",
    "para_id": "142001_177",
    "type": "paragraph",
    "text": "(1)콘크리트의 회복될 수 없는 처짐과 길이방향 쪼갬 균열 발생을 방지하기 위하여 콘크리트의 압축응력을 제한하여야 한다. (2)철근과 긴장재는 제어할 수 없는 균열을 예방할 수 있는 적당한 안전율을 갖도록 인장응력을 제한하여야 한다. (3)구조물의 기능과 내구성을 손상시키거나 또는 외관상 수용할 수 없을 정도의 균열이 발생하지 않도록 균열폭을 제한하여야 한다. (4)콘크리트 부재 또는 구조물의 처짐이 이들의 기능 또는 외관에 심각한 영향을 주지 않도록 적절한 처짐한계를 설정하여야 한다. (5)사용자에게 미치는 불안감, 기계의 작동에 대한 영향, 부재의 균열 및 피복손실 등을 고려하여 구조물의 진동한계를 설정하여야 한다."
  },
  {
    "doc_id": "142001",
    "para_id": "142001_178",
    "type": "header",
    "level": 2,
    "text": "8.3 성능검증"
  },
  {
    "doc_id": "142001",
    "para_id": "142001_179",
    "type": "paragraph",
    "text": "(1)부재의 사용성능은 부록 4의 규정에 제시되는 기본구조요소 모델과 재료의 성질을 반영한 역학 이론에 근거한 해석 모델 또는 실험에 의하여 검증하여야 한다. (2)예상 가능한 하중조합의 영향이 부재의 사용한계상태를 초과하지 않는다는 것을 검증하여야 한다. (3)사용성능을 검토할 때 특별히 지정하지 않는 한, 재료의 강도감소계수는 1.0을 취하여야 한다. (4)콘크리트의 균열폭은 인접 균열 사이의 콘크리트와 철근의 평균 변형률 차이와 최대 균열 간격을 곱하여 구할 수 있다. (5)부재의 처짐은 단면의 모멘트-곡률 관계를 기초로 계산할 수 있다. (6)콘크리트의 장기처짐 평가에서는 지속하중에 의한 시간 의존적 장기거동을 고려하여야 한다. (7)구조물 또는 구조 부재의 진동은 고유진동수 또는 진동가속도 항으로 검증할 수 있다. (8)사용성능을 평가할 때 온도 또는 수축과 같은 변형하중의 영향을 고려하여야 한다."
  },
  {
    "doc_id": "142001",
    "para_id": "142001_180",
    "type": "header",
    "level": 1,
    "text": "9. 내구성능검증"
  },
  {
    "doc_id": "142001",
    "para_id": "142001_181",
    "type": "header",
    "level": 2,
    "text": "9.1 일반사항"
  },
  {
    "doc_id": "142001",
    "para_id": "142001_182",
    "type": "paragraph",
    "text": "(1)이 규정은 콘크리트 구조물이 설계내구수명동안 노출 환경 영향으로 인하여 구조적 일체성을 잃지 않도록 설계되었는지를 검증하기 위하여 적용하여야 한다. (2)발주자는 구조물의 요구내구수명을 결정하여야 하며, 설계자는 콘크리트 구조물이 실제로 건설되는 위치의 환경조건을 고려하여 노출환경조건을 결정하여야 한다. (3)구조물이 요구내구수명 동안 최소한의 유지보수로 기능을 유지하고 검사 및 유지보수를 위하여 모든 부분에 접근이 용이하도록 설계하여야 한다. (4)구조물의 노출 환경조건, 사용수명, 환경하중의 집중 등을 고려하여 구조물의 형태와 보강재의 피복 두께를 정하여야 한다. (5)설계할 때 가정된 콘크리트의 요구물성이 충족되도록 콘크리트의 배합이 이루어져야 한다."
  },
  {
    "doc_id": "142001",
    "para_id": "142001_183",
    "type": "header",
    "level": 2,
    "text": "9.2 성능저하인자의 한계상태 설정"
  },
  {
    "doc_id": "142001",
    "para_id": "142001_184",
    "type": "paragraph",
    "text": "(1)염해에 대한 내구성능 한계상태는 철근부식이 시작되는 때로 할 수 있다. (2)탄산화에 대한 내구성능 한계상태는 탄산화 깊이가 최외측 철근의 표면에 도달할 때로 할 수 있다. (3)동해에 대한 내구성능 한계상태는 콘크리트의 표면박리 및 균열이 발생할 때의 최소 상대동탄성계수로 할 수 있다. (4)황산염 침식에 대한 내구성능 한계상태는 황산염의 침투가 최외측 철근의 표면에 도달할 때로 할 수 있다."
  },
  {
    "doc_id": "142001",
    "para_id": "142001_185",
    "type": "header",
    "level": 2,
    "text": "9.3 성능검증"
  },
  {
    "doc_id": "142001",
    "para_id": "142001_186",
    "type": "paragraph",
    "text": "(1)콘크리트 구조물의 내구성능평가는 성능저하의 기구와 과정을 반영한 신뢰성 있는 방법으로 수행하여야 한다. (2)콘크리트 구조물의 내구성능을 평가할 때는 다음과 같은 성능저하인자들을 고려하여야 한다. ① 염해 ② 탄산화 ③ 동결융해 ④ 알칼리-골재 반응 ⑤ 황산염 침식 ⑥ 기타 철근부식을 유발하는 인자 (3)내구성능을 평가할 때는 각각의 노출환경조건, 성능저하인자에 대한 콘크리트의 저항특성, 피복 두께 등을 고려하여야 한다. (4)구조물의 내구성능은 각각의 성능저하요인에 대하여 평가하는 것을 원칙으로 한다. 다만, 필요할 경우 각 성능저하요인의 복합효과를 고려하여야 한다."
  },
  {
    "doc_id": "142001",
    "para_id": "142001_187",
    "type": "header",
    "level": 1,
    "text": "10. 환경성능검증"
  },
  {
    "doc_id": "142001",
    "para_id": "142001_188",
    "type": "header",
    "level": 2,
    "text": "10.1 일반 사항"
  },
  {
    "doc_id": "142001",
    "para_id": "142001_189",
    "type": "paragraph",
    "text": "(1)콘크리트 구조물의 전 과정에 대한 환경성능검증은 설계단계에서 이루어져야 한다. 여기서, 콘크리트 구조물의 전 과정은 설계, 시공, 유지관리, 해체, 폐기, 폐기물의 재활용을 포함한다. (2)환경에 미치는 영향을 고려한 요구환경성능은 자원 및 에너지의 사용, 오염물질 배출, 자원 재활용 등에 대해 정량적으로 표시되어야 한다. (3)콘크리트 구조물의 환경성능검증은 환경에 미치는 영향을 고려한 적절한 지표를 이용하여야 하며 구조물의 보유환경성능은 발주자나 국가기준이 정한 환경성능을 충족하여야 한다."
  },
  {
    "doc_id": "142001",
    "para_id": "142001_190",
    "type": "header",
    "level": 2,
    "text": "10.2 한계상태 설정"
  },
  {
    "doc_id": "142001",
    "para_id": "142001_191",
    "type": "paragraph",
    "text": "(1)지구온난화와 같은 지구환경, 콘크리트 구조물이 위치하는 곳의 수질 및 토양 오염과 같은 지역환경, 소음이나 진동, 오염물질의 비산과 같은 작업환경에 미치는 영향을 고려하여 적절한 환경지표를 정하여야 한다. (2)발주자는 선정된 각각의 환경지표에 대하여 환경성능 목표를 정량적으로 정하여야 한다. 이때 환경성능 목표는 최소한 국가기준에서 정한 요구환경성능을 충족시켜야 한다. (3)환경성능 목표를 충족하기 위하여 다음 사항에 대한 요구 조건을 공사 관련 도서에 명시하여야 한다. ① 재료의 선정 ② 구조설계 ③ 시공방법 ④ 유지관리 절차 ⑤ 해체 및 폐기물 처리 절차 ⑥ 에너지 및 자원의 소비한계 ⑦ 이산화탄소 배출, 수질오염, 토양오염, 분진, 진동 및 화학물질의 한계"
  },
  {
    "doc_id": "142001",
    "para_id": "142001_192",
    "type": "header",
    "level": 2,
    "text": "10.3 성능검증"
  },
  {
    "doc_id": "142001",
    "para_id": "142001_193",
    "type": "paragraph",
    "text": "(1)콘크리트 구조물의 보유환경성능은 선정된 환경지표에 대하여 국가기준 또는 국가에서 인정하는 단체에서 정한 표준방법으로 평가하여야 한다. (2)콘크리트 구조물의 보유환경성능이 발주자가 정한 요구환경성능을 만족하는지에 대하여 검증하여야 한다."
  }
]